ziggurat_foundations/__init__.py
ziggurat_foundations/exc.py
ziggurat_foundations/permissions.py
ziggurat_foundations/utils.py
ziggurat_foundations/ext/__init__.py
ziggurat_foundations/ext/pyramid/__init__.py
ziggurat_foundations/ext/pyramid/get_user.py
ziggurat_foundations/ext/pyramid/sign_in.py
ziggurat_foundations/migrations/__init__.py
ziggurat_foundations/migrations/env.py
ziggurat_foundations/migrations/versions/13391c68750_add_security_code_date.py
ziggurat_foundations/migrations/versions/20671b28c538_change_all_linking_k.py
ziggurat_foundations/migrations/versions/24ab8d11f014_external_identities.py
ziggurat_foundations/migrations/versions/264049f80948_create_ordering_colu.py
ziggurat_foundations/migrations/versions/2bb1ba973f0b_initial_structure.py
ziggurat_foundations/migrations/versions/2d472fe79b95_bigger_identity_data.py
ziggurat_foundations/migrations/versions/3cfc41c4a5f0_groups_pkey_change.py
ziggurat_foundations/migrations/versions/438c27ec1c9_normalize_constraint_and_key_names.py
ziggurat_foundations/migrations/versions/439766f6104d_add_lower_indexes_to.py
ziggurat_foundations/migrations/versions/46a9c4fb9560_pass_col_sizes.py
ziggurat_foundations/migrations/versions/4c10d97c509_add_index_to_resourc.py
ziggurat_foundations/migrations/versions/53927300c277_change_primary_key_s.py
ziggurat_foundations/migrations/versions/54d08f9adc8c_add_registered_date_.py
ziggurat_foundations/migrations/versions/57bbf0c387c_add_local_user_id.py
ziggurat_foundations/migrations/versions/5c84d7260c5_add_parent_id.py
ziggurat_foundations/migrations/versions/613e7c11dead_create_indices_on_resource_owners.py
ziggurat_foundations/migrations/versions/b5e6dd3449dd_increase_field_sizes.py
ziggurat_foundations/models/__init__.py
ziggurat_foundations/models/base.py
ziggurat_foundations/models/external_identity.py
ziggurat_foundations/models/group.py
ziggurat_foundations/models/group_permission.py
ziggurat_foundations/models/group_resource_permission.py
ziggurat_foundations-0.9.1.dist-info/LICENSE
ziggurat_foundations-0.9.1.dist-info/METADATA
ziggurat_foundations-0.9.1.dist-info/WHEEL
ziggurat_foundations-0.9.1.dist-info/top_level.txt
ziggurat_foundations-0.9.1.dist-info/zip-safe
ziggurat_foundations-0.9.1.dist-info/RECORD
