Metadata-Version: 2.1
Name: ziggurat-foundations
Version: 0.9.1
Summary: Set of SQLAlchemy mixins that make application building an easy task. Provides users, groups,
Home-page: https://github.com/ergo/ziggurat_foundations
Author: Marcin Lulek
Author-email: info@webreactor.eu
License: BSD
Platform: UNKNOWN
Classifier: Development Status :: 5 - Production/Stable
Classifier: Framework :: Flask
Classifier: Framework :: Pylons
Classifier: Framework :: Pyramid
Classifier: License :: OSI Approved :: BSD License
Classifier: Programming Language :: Python :: 3
License-File: LICENSE
Requires-Dist: alembic
Requires-Dist: paginate
Requires-Dist: paginate-sqlalchemy
Requires-Dist: passlib (>=1.6.1)
Requires-Dist: six
Requires-Dist: sqlalchemy
Requires-Dist: zope.deprecation (>=3.5.0)
Provides-Extra: lint
Requires-Dist: black ; extra == 'lint'
Requires-Dist: flake8 ; extra == 'lint'
Requires-Dist: pylint ; extra == 'lint'
Requires-Dist: rstcheck ; extra == 'lint'
Provides-Extra: test
Requires-Dist: coverage ; extra == 'test'
Requires-Dist: mock ; extra == 'test'
Requires-Dist: pyramid ; extra == 'test'
Requires-Dist: pyramid-jinja2 ; extra == 'test'
Requires-Dist: pytest ; extra == 'test'
Requires-Dist: pytest-cov ; extra == 'test'
Requires-Dist: tox ; extra == 'test'
Requires-Dist: webtest ; extra == 'test'
